RsCmwCdma2kSig/RsCmwCdma2kSig.py
RsCmwCdma2kSig/__init__.py
RsCmwCdma2kSig/enums.py
RsCmwCdma2kSig/repcap.py
RsCmwCdma2kSig/CustomFiles/__init__.py
RsCmwCdma2kSig/CustomFiles/events.py
RsCmwCdma2kSig/CustomFiles/reliability.py
RsCmwCdma2kSig/CustomFiles/utilities.py
RsCmwCdma2kSig/Implementations/Call.py
RsCmwCdma2kSig/Implementations/Clean.py
RsCmwCdma2kSig/Implementations/Configure.py
RsCmwCdma2kSig/Implementations/Route.py
RsCmwCdma2kSig/Implementations/RxQuality.py
RsCmwCdma2kSig/Implementations/Sense.py
RsCmwCdma2kSig/Implementations/Soption.py
RsCmwCdma2kSig/Implementations/Source.py
RsCmwCdma2kSig/Implementations/__init__.py
RsCmwCdma2kSig/Implementations/Call_/Handoff.py
RsCmwCdma2kSig/Implementations/Call_/Otasp.py
RsCmwCdma2kSig/Implementations/Call_/Pdm.py
RsCmwCdma2kSig/Implementations/Call_/Reconfigure.py
RsCmwCdma2kSig/Implementations/Call_/Soption.py
RsCmwCdma2kSig/Implementations/Call_/__init__.py
RsCmwCdma2kSig/Implementations/Call_/Otasp_/Receive.py
RsCmwCdma2kSig/Implementations/Call_/Otasp_/Send.py
RsCmwCdma2kSig/Implementations/Call_/Otasp_/__init__.py
RsCmwCdma2kSig/Implementations/Call_/Pdm_/Receive.py
RsCmwCdma2kSig/Implementations/Call_/Pdm_/Send.py
RsCmwCdma2kSig/Implementations/Call_/Pdm_/__init__.py
RsCmwCdma2kSig/Implementations/Clean_/Sms.py
RsCmwCdma2kSig/Implementations/Clean_/__init__.py
RsCmwCdma2kSig/Implementations/Clean_/Sms_/Incoming.py
RsCmwCdma2kSig/Implementations/Clean_/Sms_/__init__.py
RsCmwCdma2kSig/Implementations/Clean_/Sms_/Incoming_/Info.py
RsCmwCdma2kSig/Implementations/Clean_/Sms_/Incoming_/__init__.py
RsCmwCdma2kSig/Implementations/Configure_/Capabilities.py
RsCmwCdma2kSig/Implementations/Configure_/Connection.py
RsCmwCdma2kSig/Implementations/Configure_/Cstatus.py
RsCmwCdma2kSig/Implementations/Configure_/Fading.py
RsCmwCdma2kSig/Implementations/Configure_/Handoff.py
RsCmwCdma2kSig/Implementations/Configure_/IqIn.py
RsCmwCdma2kSig/Implementations/Configure_/Layer.py
RsCmwCdma2kSig-3.8.10.24.dist-info/METADATA
RsCmwCdma2kSig-3.8.10.24.dist-info/WHEEL
RsCmwCdma2kSig-3.8.10.24.dist-info/top_level.txt
RsCmwCdma2kSig-3.8.10.24.dist-info/RECORD
